slgs1/__init__.py
slgs1/tweet_crawler.py
slgs1-0.0.7.dist-info/METADATA
slgs1-0.0.7.dist-info/WHEEL
slgs1-0.0.7.dist-info/license.txt
slgs1-0.0.7.dist-info/top_level.txt
slgs1-0.0.7.dist-info/RECORD
